slowcli/__init__.py
slowcli/cli.py
slowcli/cli_completion.py
slowcli/cli_snapshot.json
slowcli/main.py
slowcli/main_completion.py
slowcli/main_snapshot.json
slowcli/utils.py
slowcli/commands/__init__.py
slowcli/commands/analysis_commands.py
slowcli/commands/data_commands.py
slowcli/commands/network_commands.py
slowcli/commands/system_commands.py
slowcli-0.1.7.dist-info/licenses/LICENSE
slowcli-0.1.7.dist-info/METADATA
slowcli-0.1.7.dist-info/WHEEL
slowcli-0.1.7.dist-info/entry_points.txt
slowcli-0.1.7.dist-info/top_level.txt
slowcli-0.1.7.dist-info/RECORD
